[
    {
        "nombre": "HTML",
        "img": "/assets/logos/logo-html.svg",
        "area": "font-end"
    },
    {
        "nombre": "CSS",
        "img": "/assets/logos/logo-css.svg",
        "area": "font-end"
    },
    {
        "nombre": "JAVASCRIPT",
        "img": "/assets/logos/logo-js.svg",
        "area": "font-end"
    },
    {
        "nombre": "PHP",
        "img": "/assets/logos/php.png",
        "area": "back-end"
    },
    {
        "nombre": "REACT JS",
        "img": "/assets/logos/logo-react.svg",
        "area": "font-end"
    },
    {
        "nombre": "LARAVEL",
        "img": "/assets/logos/logo-laravel.svg",
        "area": "back-end"
    },
    {
        "nombre": "ASTRO",
        "img": "/assets/logos/logo-astro.svg",
        "area": "font-end"
    },
    {
        "nombre": "BOOTSTRAP",
        "img": "/assets/logos/bootstrap.png",
        "area": "font-end"
    },
    {
        "nombre": "TAILWIND",
        "img": "/assets/logos/logo-tailwind.svg",
        "area": "font-end"
    },
    {
        "nombre": "MYSQL",
        "img": "/assets/logos/logo-mysql.png",
        "area": "back-end"
    },
    {
        "nombre": "SQLServer",
        "img": "/assets/logos/sql-server.png",
        "area": "back-end"
    },
    {
        "nombre": "POSTGRE",
        "img": "/assets/logos/postgreSQL.png",
        "area": "back-end"
    },
    {
        "nombre": "POSTMAN",
        "img": "/assets/logos/logo-postman.svg",
        "area": "back-end"
    },
    {
        "nombre": "GIT",
        "img": "/assets/logos/logo-git.png",
        "area": "back-end"
    }
]